muranoclient/__init__.py
muranoclient/client.py
muranoclient/i18n.py
muranoclient/shell.py
muranoclient/version.py
muranoclient/apiclient/__init__.py
muranoclient/apiclient/auth.py
muranoclient/apiclient/base.py
muranoclient/apiclient/client.py
muranoclient/apiclient/exceptions.py
muranoclient/apiclient/fake_client.py
muranoclient/common/__init__.py
muranoclient/common/base.py
muranoclient/common/exceptions.py
muranoclient/common/http.py
muranoclient/common/utils.py
muranoclient/common/yaqlexpression.py
muranoclient/common/yaqlexpression_legacy.py
muranoclient/data/heat_logo.png
muranoclient/data/mpl_logo.png
muranoclient/glance/__init__.py
muranoclient/glance/artifacts.py
muranoclient/glance/client.py
muranoclient/locale/en_GB/LC_MESSAGES/muranoclient.po
muranoclient/osc/__init__.py
muranoclient/osc/plugin.py
muranoclient/osc/v1/__init__.py
muranoclient/osc/v1/action.py
muranoclient/osc/v1/category.py
muranoclient/osc/v1/deployment.py
muranoclient/osc/v1/environment.py
muranoclient/osc/v1/package.py
muranoclient/osc/v1/schema.py
muranoclient/tests/__init__.py
muranoclient/tests/functional/__init__.py
muranoclient/tests/functional/muranoclient.py
muranoclient/tests/functional/cli/__init__.py
muranoclient/tests/functional/cli/murano_test_utils.py
muranoclient/tests/functional/cli/test_murano.py
muranoclient/tests/functional/cli/utils.py
muranoclient/tests/functional/cli/MockApp/Classes/mock_muranopl.yaml
muranoclient/tests/unit/__init__.py
muranoclient/tests/unit/base.py
muranoclient/tests/unit/fakes.py
muranoclient/tests/unit/test_base.py
muranoclient/tests/unit/test_common_http.py
muranoclient/tests/unit/test_exc.py
muranoclient/tests/unit/test_methods.py
muranoclient/tests/unit/test_package_creator.py
muranoclient/tests/unit/test_shell.py
muranoclient/tests/unit/test_utils.py
muranoclient/tests/unit/fixture_data/heat-template.yaml
muranoclient/tests/unit/fixture_data/logo.png
muranoclient/tests/unit/fixture_data/empty-app/manifest.yaml
python_muranoclient-2.8.0.dist-info/AUTHORS
python_muranoclient-2.8.0.dist-info/LICENSE
python_muranoclient-2.8.0.dist-info/METADATA
python_muranoclient-2.8.0.dist-info/WHEEL
python_muranoclient-2.8.0.dist-info/entry_points.txt
python_muranoclient-2.8.0.dist-info/pbr.json
python_muranoclient-2.8.0.dist-info/top_level.txt
python_muranoclient-2.8.0.dist-info/RECORD
